source_pinterest/__init__.py
source_pinterest/components/components.py
source_pinterest/manifest.yaml
source_pinterest/run.py
source_pinterest/source.py
airbyte_source_pinterest-2.1.12.dist-info/METADATA
airbyte_source_pinterest-2.1.12.dist-info/WHEEL
airbyte_source_pinterest-2.1.12.dist-info/entry_points.txt
airbyte_source_pinterest-2.1.12.dist-info/RECORD
