Metadata-Version: 2.1
Name: airbyte-source-pinterest
Version: 2.1.12
Summary: Source implementation for Pinterest.
Home-page: https://airbyte.com
License: ELv2
Author: Airbyte
Author-email: contact@airbyte.io
Requires-Python: >=3.10,<3.12
Classifier: License :: Other/Proprietary License
Classifier: Programming Language :: Python :: 3
Classifier: Programming Language :: Python :: 3.10
Classifier: Programming Language :: Python :: 3.11
Requires-Dist: airbyte-cdk (>=7,<8)
Requires-Dist: pendulum (==2.1.2)
Project-URL: Documentation, https://docs.airbyte.com/integrations/sources/pinterest
Project-URL: Repository, https://github.com/airbytehq/airbyte
